__init__.py
example.py
javaCollectionInPython/__init__.py
javaCollectionInPython/bitset.py
javaCollectionInPython-0.0.7.dist-info/LICENSE
javaCollectionInPython-0.0.7.dist-info/METADATA
javaCollectionInPython-0.0.7.dist-info/WHEEL
javaCollectionInPython-0.0.7.dist-info/top_level.txt
javaCollectionInPython-0.0.7.dist-info/RECORD
