Metadata-Version: 2.1
Name: javaCollectionInPython
Version: 0.0.7
Summary: The java collection in python implementation. Now it includes BitSet
Author-email: scugxl <gaoxingliang@outlook.com>
License: Apache License
Project-URL: Homepage, https://github.com/gaoxingliang/java-collection-in-python
Project-URL: Bug Tracker, https://github.com/gaoxingliang/java-collection-in-python/issues
Classifier: Programming Language :: Python :: 3
Classifier: License :: OSI Approved :: MIT License
Classifier: Operating System :: OS Independent
Requires-Python: >=3
License-File: LICENSE
